{
	"name": "DF_online_sales",
	"properties": {
		"folder": {
			"name": "DF_Neelima"
		},
		"type": "MappingDataFlow",
		"typeProperties": {
			"sources": [
				{
					"dataset": {
						"referenceName": "DS_src_online_retail",
						"type": "DatasetReference"
					},
					"name": "source1"
				}
			],
			"sinks": [
				{
					"dataset": {
						"referenceName": "DS_tgt_online_retail",
						"type": "DatasetReference"
					},
					"name": "sink1"
				}
			],
			"transformations": [
				{
					"name": "derivedColumn1"
				},
				{
					"name": "select1"
				}
			],
			"scriptLines": [
				"source(output(",
				"          InvoiceNo as string,",
				"          StockCode as string,",
				"          Description as string,",
				"          Quantity as string,",
				"          InvoiceDate as string,",
				"          UnitPrice as string,",
				"          CustomerID as string,",
				"          Country as string",
				"     ),",
				"     allowSchemaDrift: true,",
				"     validateSchema: false,",
				"     ignoreNoFilesFound: false) ~> source1",
				"source1 derive(Chn_invoiceno = toInteger(InvoiceNo),",
				"          Cnh_quantity = toInteger(Quantity),",
				"          Chn_customerid = toInteger(CustomerID),",
				"          Chn_unitprice = toFloat(UnitPrice)) ~> derivedColumn1",
				"derivedColumn1 select(mapColumn(",
				"          InvoiceNo = Chn_invoiceno,",
				"          StockCode,",
				"          Description,",
				"          Quantity = Cnh_quantity,",
				"          InvoiceDate,",
				"          UnitPrice = Chn_unitprice,",
				"          CustomerID = Chn_customerid,",
				"          Country",
				"     ),",
				"     skipDuplicateMapInputs: true,",
				"     skipDuplicateMapOutputs: true) ~> select1",
				"select1 sink(allowSchemaDrift: true,",
				"     validateSchema: false,",
				"     input(",
				"          invoiceno as long,",
				"          stockcode as string,",
				"          descriptions as string,",
				"          quantity as long,",
				"          invoicedate as string,",
				"          unitprice as integer,",
				"          customerid as long,",
				"          country as string",
				"     ),",
				"     deletable:false,",
				"     insertable:true,",
				"     updateable:false,",
				"     upsertable:false,",
				"     format: 'table',",
				"     skipDuplicateMapInputs: true,",
				"     skipDuplicateMapOutputs: true,",
				"     errorHandlingOption: 'stopOnFirstError',",
				"     mapColumn(",
				"          invoiceno = InvoiceNo,",
				"          stockcode = StockCode,",
				"          descriptions = Description,",
				"          quantity = Quantity,",
				"          invoicedate = InvoiceDate,",
				"          unitprice = UnitPrice,",
				"          customerid = CustomerID,",
				"          country = Country",
				"     )) ~> sink1"
			]
		}
	}
}